[
  {
    "comp": "1624702",
    "jour": "2025-11-22",
    "hippo": "Paris-Vincennes",
    "prixnom": "Prix de Bagnoles-de-l'Orne (Prix Daniel Miette)",
    "predictions": [
      {
        "comp": "1624702",
        "jour": "2025-11-22",
        "hippo": "Paris-Vincennes",
        "reun": "1",
        "prix": "4",
        "prixnom": "Prix de Bagnoles-de-l'Orne (Prix Daniel Miette)",
        "numero": 7,
        "idche": 1461252,
        "age": 7,
        "entraineur": "A. Chavatte",
        "cotedirect": 6.0,
        "predicted_position": 3.2764782905578613,
        "predicted_position_tabnet": 4.871781349182129,
        "predicted_position_rf": 5.853474140167236,
        "raw_rf_prediction": 5.853474140167236,
        "raw_tabnet_prediction": 4.871781349182129,
        "predicted_position_base": 5.460797309875488,
        "predicted_rank": 1
      },
      {
        "comp": "1624702",
        "jour": "2025-11-22",
        "hippo": "Paris-Vincennes",
        "reun": "1",
        "prix": "4",
        "prixnom": "Prix de Bagnoles-de-l'Orne (Prix Daniel Miette)",
        "numero": 15,
        "idche": 1471966,
        "age": 7,
        "entraineur": "T. Levesque",
        "cotedirect": 2.8,
        "predicted_position": 3.7528302669525146,
        "predicted_position_tabnet": 4.712523460388184,
        "predicted_position_rf": 5.7936272621154785,
        "raw_rf_prediction": 5.7936272621154785,
        "raw_tabnet_prediction": 4.712523460388184,
        "predicted_position_base": 5.3611860275268555,
        "predicted_rank": 2
      },
      {
        "comp": "1624702",
        "jour": "2025-11-22",
        "hippo": "Paris-Vincennes",
        "reun": "1",
        "prix": "4",
        "prixnom": "Prix de Bagnoles-de-l'Orne (Prix Daniel Miette)",
        "numero": 10,
        "idche": 1435315,
        "age": 8,
        "entraineur": "P. Boutin",
        "cotedirect": 15.0,
        "predicted_position": 4.1449875831604,
        "predicted_position_tabnet": 6.239407539367676,
        "predicted_position_rf": 8.400961875915527,
        "raw_rf_prediction": 8.400961875915527,
        "raw_tabnet_prediction": 6.239407539367676,
        "predicted_position_base": 7.536340713500977,
        "predicted_rank": 3
      },
      {
        "comp": "1624702",
        "jour": "2025-11-22",
        "hippo": "Paris-Vincennes",
        "reun": "1",
        "prix": "4",
        "prixnom": "Prix de Bagnoles-de-l'Orne (Prix Daniel Miette)",
        "numero": 11,
        "idche": 1387968,
        "age": 8,
        "entraineur": "Mme S. Raimond",
        "cotedirect": 5.9,
        "predicted_position": 4.591453552246094,
        "predicted_position_tabnet": 5.424627304077148,
        "predicted_position_rf": 6.586811542510986,
        "raw_rf_prediction": 6.586811542510986,
        "raw_tabnet_prediction": 5.424627304077148,
        "predicted_position_base": 6.121938228607178,
        "predicted_rank": 4
      },
      {
        "comp": "1624702",
        "jour": "2025-11-22",
        "hippo": "Paris-Vincennes",
        "reun": "1",
        "prix": "4",
        "prixnom": "Prix de Bagnoles-de-l'Orne (Prix Daniel Miette)",
        "numero": 6,
        "idche": 1350394,
        "age": 9,
        "entraineur": "P. Boutin",
        "cotedirect": 36.0,
        "predicted_position": 4.887765407562256,
        "predicted_position_tabnet": 8.61915397644043,
        "predicted_position_rf": 9.0653076171875,
        "raw_rf_prediction": 9.0653076171875,
        "raw_tabnet_prediction": 8.61915397644043,
        "predicted_position_base": 8.886846542358398,
        "predicted_rank": 5
      },
      {
        "comp": "1624702",
        "jour": "2025-11-22",
        "hippo": "Paris-Vincennes",
        "reun": "1",
        "prix": "4",
        "prixnom": "Prix de Bagnoles-de-l'Orne (Prix Daniel Miette)",
        "numero": 13,
        "idche": 1492441,
        "age": 7,
        "entraineur": "J. Le Mer",
        "cotedirect": 9.4,
        "predicted_position": 5.049975395202637,
        "predicted_position_tabnet": 5.445122241973877,
        "predicted_position_rf": 7.592085361480713,
        "raw_rf_prediction": 7.592085361480713,
        "raw_tabnet_prediction": 5.445122241973877,
        "predicted_position_base": 6.73330020904541,
        "predicted_rank": 6
      },
      {
        "comp": "1624702",
        "jour": "2025-11-22",
        "hippo": "Paris-Vincennes",
        "reun": "1",
        "prix": "4",
        "prixnom": "Prix de Bagnoles-de-l'Orne (Prix Daniel Miette)",
        "numero": 3,
        "idche": 1438306,
        "age": 8,
        "entraineur": "T. Raffegeau",
        "cotedirect": 35.0,
        "predicted_position": 5.084201335906982,
        "predicted_position_tabnet": 8.767290115356445,
        "predicted_position_rf": 8.277920722961426,
        "raw_rf_prediction": 8.277920722961426,
        "raw_tabnet_prediction": 8.767290115356445,
        "predicted_position_base": 8.473669052124023,
        "predicted_rank": 7
      },
      {
        "comp": "1624702",
        "jour": "2025-11-22",
        "hippo": "Paris-Vincennes",
        "reun": "1",
        "prix": "4",
        "prixnom": "Prix de Bagnoles-de-l'Orne (Prix Daniel Miette)",
        "numero": 9,
        "idche": 1534739,
        "age": 7,
        "entraineur": "JF. Mary",
        "cotedirect": 11.0,
        "predicted_position": 5.2659687995910645,
        "predicted_position_tabnet": 5.693527698516846,
        "predicted_position_rf": 8.742335319519043,
        "raw_rf_prediction": 8.742335319519043,
        "raw_tabnet_prediction": 5.693527698516846,
        "predicted_position_base": 7.522812843322754,
        "predicted_rank": 8
      },
      {
        "comp": "1624702",
        "jour": "2025-11-22",
        "hippo": "Paris-Vincennes",
        "reun": "1",
        "prix": "4",
        "prixnom": "Prix de Bagnoles-de-l'Orne (Prix Daniel Miette)",
        "numero": 4,
        "idche": 1430387,
        "age": 8,
        "entraineur": "A. Chavatte",
        "cotedirect": 25.0,
        "predicted_position": 6.41351318359375,
        "predicted_position_tabnet": 6.868404865264893,
        "predicted_position_rf": 9.673314094543457,
        "raw_rf_prediction": 9.673314094543457,
        "raw_tabnet_prediction": 6.868404865264893,
        "predicted_position_base": 8.551350593566895,
        "predicted_rank": 9
      },
      {
        "comp": "1624702",
        "jour": "2025-11-22",
        "hippo": "Paris-Vincennes",
        "reun": "1",
        "prix": "4",
        "prixnom": "Prix de Bagnoles-de-l'Orne (Prix Daniel Miette)",
        "numero": 8,
        "idche": 1496943,
        "age": 7,
        "entraineur": "JM. Chaineux",
        "cotedirect": 25.0,
        "predicted_position": 6.569215774536133,
        "predicted_position_tabnet": 7.228313446044922,
        "predicted_position_rf": 10.822113990783691,
        "raw_rf_prediction": 10.822113990783691,
        "raw_tabnet_prediction": 7.228313446044922,
        "predicted_position_base": 9.384593963623047,
        "predicted_rank": 10
      },
      {
        "comp": "1624702",
        "jour": "2025-11-22",
        "hippo": "Paris-Vincennes",
        "reun": "1",
        "prix": "4",
        "prixnom": "Prix de Bagnoles-de-l'Orne (Prix Daniel Miette)",
        "numero": 2,
        "idche": 1384902,
        "age": 8,
        "entraineur": "JR. Delliaux",
        "cotedirect": 168.0,
        "predicted_position": 7.419622898101807,
        "predicted_position_tabnet": 10.734673500061035,
        "predicted_position_rf": 10.509319305419922,
        "raw_rf_prediction": 10.509319305419922,
        "raw_tabnet_prediction": 10.734673500061035,
        "predicted_position_base": 10.599461555480957,
        "predicted_rank": 11
      },
      {
        "comp": "1624702",
        "jour": "2025-11-22",
        "hippo": "Paris-Vincennes",
        "reun": "1",
        "prix": "4",
        "prixnom": "Prix de Bagnoles-de-l'Orne (Prix Daniel Miette)",
        "numero": 1,
        "idche": 1433230,
        "age": 7,
        "entraineur": "J. Vanmeerbeck",
        "cotedirect": 146.0,
        "predicted_position": 7.590800762176514,
        "predicted_position_tabnet": 10.230457305908203,
        "predicted_position_rf": 11.253028869628906,
        "raw_rf_prediction": 11.253028869628906,
        "raw_tabnet_prediction": 10.230457305908203,
        "predicted_position_base": 10.844000816345215,
        "predicted_rank": 12
      },
      {
        "comp": "1624702",
        "jour": "2025-11-22",
        "hippo": "Paris-Vincennes",
        "reun": "1",
        "prix": "4",
        "prixnom": "Prix de Bagnoles-de-l'Orne (Prix Daniel Miette)",
        "numero": 5,
        "idche": 1339029,
        "age": 9,
        "entraineur": "A. De Jésus",
        "cotedirect": 190.0,
        "predicted_position": 7.611246109008789,
        "predicted_position_tabnet": 10.729347229003906,
        "predicted_position_rf": 10.969117164611816,
        "raw_rf_prediction": 10.969117164611816,
        "raw_tabnet_prediction": 10.729347229003906,
        "predicted_position_base": 10.873208999633789,
        "predicted_rank": 13
      },
      {
        "comp": "1624702",
        "jour": "2025-11-22",
        "hippo": "Paris-Vincennes",
        "reun": "1",
        "prix": "4",
        "prixnom": "Prix de Bagnoles-de-l'Orne (Prix Daniel Miette)",
        "numero": 16,
        "idche": 1389223,
        "age": 8,
        "entraineur": "C. Thomain",
        "cotedirect": 90.0,
        "predicted_position": 7.8399739265441895,
        "predicted_position_tabnet": 10.155424118041992,
        "predicted_position_rf": 11.896321296691895,
        "raw_rf_prediction": 11.896321296691895,
        "raw_tabnet_prediction": 10.155424118041992,
        "predicted_position_base": 11.199962615966797,
        "predicted_rank": 14
      },
      {
        "comp": "1624702",
        "jour": "2025-11-22",
        "hippo": "Paris-Vincennes",
        "reun": "1",
        "prix": "4",
        "prixnom": "Prix de Bagnoles-de-l'Orne (Prix Daniel Miette)",
        "numero": 14,
        "idche": 1449389,
        "age": 7,
        "entraineur": "J. Cuoq",
        "cotedirect": 21.0,
        "predicted_position": 7.901199817657471,
        "predicted_position_tabnet": 8.972733497619629,
        "predicted_position_rf": 11.576398849487305,
        "raw_rf_prediction": 11.576398849487305,
        "raw_tabnet_prediction": 8.972733497619629,
        "predicted_position_base": 10.534933090209961,
        "predicted_rank": 15
      },
      {
        "comp": "1624702",
        "jour": "2025-11-22",
        "hippo": "Paris-Vincennes",
        "reun": "1",
        "prix": "4",
        "prixnom": "Prix de Bagnoles-de-l'Orne (Prix Daniel Miette)",
        "numero": 12,
        "idche": 1448183,
        "age": 9,
        "entraineur": "D. Locqueneux",
        "cotedirect": 101.0,
        "predicted_position": 8.251382827758789,
        "predicted_position_tabnet": 11.036832809448242,
        "predicted_position_rf": 10.978517532348633,
        "raw_rf_prediction": 10.978517532348633,
        "raw_tabnet_prediction": 11.036832809448242,
        "predicted_position_base": 11.00184440612793,
        "predicted_rank": 16
      }
    ]
  }
]