[
  {
    "comp": "1612996",
    "jour": "2025-10-06",
    "hippo": "Enghien",
    "prixnom": "Prix du Pont des Arts",
    "predictions": [
      {
        "comp": "1612996",
        "jour": "2025-10-06",
        "hippo": "Enghien",
        "reun": "1",
        "prix": "1",
        "prixnom": "Prix du Pont des Arts",
        "numero": 3,
        "idche": 1431146,
        "age": 7,
        "entraineur": "H. Van den Hende",
        "cotedirect": 10.0,
        "predicted_position": 3.6508429050445557,
        "predicted_position_tabnet": 5.248460292816162,
        "predicted_position_rf": 5.207246780395508,
        "raw_rf_prediction": 5.207246780395508,
        "raw_tabnet_prediction": 5.248460292816162,
        "predicted_position_base": 5.215489864349365,
        "predicted_rank": 1
      },
      {
        "comp": "1612996",
        "jour": "2025-10-06",
        "hippo": "Enghien",
        "reun": "1",
        "prix": "1",
        "prixnom": "Prix du Pont des Arts",
        "numero": 13,
        "idche": 1457376,
        "age": 7,
        "entraineur": "D. Bonne",
        "cotedirect": 3.9,
        "predicted_position": 4.390321254730225,
        "predicted_position_tabnet": 3.9794907569885254,
        "predicted_position_rf": 8.98313045501709,
        "raw_rf_prediction": 8.98313045501709,
        "raw_tabnet_prediction": 3.9794907569885254,
        "predicted_position_base": 7.982402324676514,
        "predicted_rank": 2
      },
      {
        "comp": "1612996",
        "jour": "2025-10-06",
        "hippo": "Enghien",
        "reun": "1",
        "prix": "1",
        "prixnom": "Prix du Pont des Arts",
        "numero": 7,
        "idche": 1469007,
        "age": 7,
        "entraineur": "P. Daugeard",
        "cotedirect": 14.0,
        "predicted_position": 4.4025373458862305,
        "predicted_position_tabnet": 6.90742301940918,
        "predicted_position_rf": 8.278910636901855,
        "raw_rf_prediction": 8.278910636901855,
        "raw_tabnet_prediction": 6.90742301940918,
        "predicted_position_base": 8.004612922668457,
        "predicted_rank": 3
      },
      {
        "comp": "1612996",
        "jour": "2025-10-06",
        "hippo": "Enghien",
        "reun": "1",
        "prix": "1",
        "prixnom": "Prix du Pont des Arts",
        "numero": 6,
        "idche": 1472472,
        "age": 7,
        "entraineur": "Emmanuel Allard (S)",
        "cotedirect": 13.0,
        "predicted_position": 4.566918849945068,
        "predicted_position_tabnet": 7.309610366821289,
        "predicted_position_rf": 7.687011241912842,
        "raw_rf_prediction": 7.687011241912842,
        "raw_tabnet_prediction": 7.309610366821289,
        "predicted_position_base": 7.6115312576293945,
        "predicted_rank": 4
      },
      {
        "comp": "1612996",
        "jour": "2025-10-06",
        "hippo": "Enghien",
        "reun": "1",
        "prix": "1",
        "prixnom": "Prix du Pont des Arts",
        "numero": 4,
        "idche": 1432334,
        "age": 7,
        "entraineur": "P. Godey",
        "cotedirect": 22.0,
        "predicted_position": 5.4547038078308105,
        "predicted_position_tabnet": 6.932424545288086,
        "predicted_position_rf": 7.358066082000732,
        "raw_rf_prediction": 7.358066082000732,
        "raw_tabnet_prediction": 6.932424545288086,
        "predicted_position_base": 7.272938251495361,
        "predicted_rank": 5
      },
      {
        "comp": "1612996",
        "jour": "2025-10-06",
        "hippo": "Enghien",
        "reun": "1",
        "prix": "1",
        "prixnom": "Prix du Pont des Arts",
        "numero": 14,
        "idche": 1471736,
        "age": 7,
        "entraineur": "L. Groussard",
        "cotedirect": 3.2,
        "predicted_position": 5.742378234863281,
        "predicted_position_tabnet": 3.6616241931915283,
        "predicted_position_rf": 9.338841438293457,
        "raw_rf_prediction": 9.338841438293457,
        "raw_tabnet_prediction": 3.6616241931915283,
        "predicted_position_base": 8.203397750854492,
        "predicted_rank": 6
      },
      {
        "comp": "1612996",
        "jour": "2025-10-06",
        "hippo": "Enghien",
        "reun": "1",
        "prix": "1",
        "prixnom": "Prix du Pont des Arts",
        "numero": 1,
        "idche": 1495111,
        "age": 7,
        "entraineur": "F. Delenclos",
        "cotedirect": 34.0,
        "predicted_position": 6.031859397888184,
        "predicted_position_tabnet": 7.861562728881836,
        "predicted_position_rf": 8.087708473205566,
        "raw_rf_prediction": 8.087708473205566,
        "raw_tabnet_prediction": 7.861562728881836,
        "predicted_position_base": 8.042479515075684,
        "predicted_rank": 7
      },
      {
        "comp": "1612996",
        "jour": "2025-10-06",
        "hippo": "Enghien",
        "reun": "1",
        "prix": "1",
        "prixnom": "Prix du Pont des Arts",
        "numero": 2,
        "idche": 1456976,
        "age": 7,
        "entraineur": "A. Lannoo",
        "cotedirect": 101.0,
        "predicted_position": 6.134230613708496,
        "predicted_position_tabnet": 10.045320510864258,
        "predicted_position_rf": 11.430102348327637,
        "raw_rf_prediction": 11.430102348327637,
        "raw_tabnet_prediction": 10.045320510864258,
        "predicted_position_base": 11.153146743774414,
        "predicted_rank": 8
      },
      {
        "comp": "1612996",
        "jour": "2025-10-06",
        "hippo": "Enghien",
        "reun": "1",
        "prix": "1",
        "prixnom": "Prix du Pont des Arts",
        "numero": 10,
        "idche": 1520911,
        "age": 7,
        "entraineur": "E. Szirmay",
        "cotedirect": 14.0,
        "predicted_position": 6.411856174468994,
        "predicted_position_tabnet": 6.103411674499512,
        "predicted_position_rf": 9.923890113830566,
        "raw_rf_prediction": 9.923890113830566,
        "raw_tabnet_prediction": 6.103411674499512,
        "predicted_position_base": 9.159794807434082,
        "predicted_rank": 9
      },
      {
        "comp": "1612996",
        "jour": "2025-10-06",
        "hippo": "Enghien",
        "reun": "1",
        "prix": "1",
        "prixnom": "Prix du Pont des Arts",
        "numero": 8,
        "idche": 1446131,
        "age": 7,
        "entraineur": "Mme N. Viel-Pierre",
        "cotedirect": 14.0,
        "predicted_position": 6.5835065841674805,
        "predicted_position_tabnet": 7.489755630493164,
        "predicted_position_rf": 9.100071907043457,
        "raw_rf_prediction": 9.100071907043457,
        "raw_tabnet_prediction": 7.489755630493164,
        "predicted_position_base": 8.778008460998535,
        "predicted_rank": 10
      },
      {
        "comp": "1612996",
        "jour": "2025-10-06",
        "hippo": "Enghien",
        "reun": "1",
        "prix": "1",
        "prixnom": "Prix du Pont des Arts",
        "numero": 11,
        "idche": 1239944,
        "age": 11,
        "entraineur": "J. Julien",
        "cotedirect": 25.0,
        "predicted_position": 6.585846424102783,
        "predicted_position_tabnet": 8.147665977478027,
        "predicted_position_rf": 9.723523139953613,
        "raw_rf_prediction": 9.723523139953613,
        "raw_tabnet_prediction": 8.147665977478027,
        "predicted_position_base": 9.40835189819336,
        "predicted_rank": 11
      },
      {
        "comp": "1612996",
        "jour": "2025-10-06",
        "hippo": "Enghien",
        "reun": "1",
        "prix": "1",
        "prixnom": "Prix du Pont des Arts",
        "numero": 12,
        "idche": 1377688,
        "age": 9,
        "entraineur": "Mlle VM. Goetz",
        "cotedirect": 15.0,
        "predicted_position": 7.046861171722412,
        "predicted_position_tabnet": 5.7650146484375,
        "predicted_position_rf": 10.30351448059082,
        "raw_rf_prediction": 10.30351448059082,
        "raw_tabnet_prediction": 5.7650146484375,
        "predicted_position_base": 9.395814895629883,
        "predicted_rank": 12
      },
      {
        "comp": "1612996",
        "jour": "2025-10-06",
        "hippo": "Enghien",
        "reun": "1",
        "prix": "1",
        "prixnom": "Prix du Pont des Arts",
        "numero": 5,
        "idche": 1382940,
        "age": 8,
        "entraineur": "Mlle VM. Goetz",
        "cotedirect": 78.0,
        "predicted_position": 7.3669939041137695,
        "predicted_position_tabnet": 10.317214965820312,
        "predicted_position_rf": 10.576041221618652,
        "raw_rf_prediction": 10.576041221618652,
        "raw_tabnet_prediction": 10.317214965820312,
        "predicted_position_base": 10.524276733398438,
        "predicted_rank": 13
      },
      {
        "comp": "1612996",
        "jour": "2025-10-06",
        "hippo": "Enghien",
        "reun": "1",
        "prix": "1",
        "prixnom": "Prix du Pont des Arts",
        "numero": 9,
        "idche": 1383552,
        "age": 9,
        "entraineur": "T. Desmarres",
        "cotedirect": 35.0,
        "predicted_position": 7.639561176300049,
        "predicted_position_tabnet": 8.235797882080078,
        "predicted_position_rf": 11.583124160766602,
        "raw_rf_prediction": 11.583124160766602,
        "raw_tabnet_prediction": 8.235797882080078,
        "predicted_position_base": 10.91365909576416,
        "predicted_rank": 14
      }
    ]
  }
]