[
  {
    "comp": "1592537",
    "jour": "2025-10-05",
    "hippo": "ParisLongchamp",
    "prixnom": "Qatar Prix de l'Arc de Triomphe",
    "predictions": [
      {
        "comp": "1592537",
        "jour": "2025-10-05",
        "hippo": "ParisLongchamp",
        "reun": "1",
        "prix": "5",
        "prixnom": "Qatar Prix de l'Arc de Triomphe",
        "numero": 6,
        "idche": 1723503,
        "age": 4,
        "entraineur": "T. Sakaguchi",
        "cotedirect": 8.0,
        "predicted_position": 4.195817947387695,
        "predicted_position_tabnet": 6.168573379516602,
        "predicted_position_rf": 5.9503889083862305,
        "raw_rf_prediction": 5.9503889083862305,
        "raw_tabnet_prediction": 6.168573379516602,
        "predicted_position_base": 5.994025707244873,
        "predicted_rank": 1
      },
      {
        "comp": "1592537",
        "jour": "2025-10-05",
        "hippo": "ParisLongchamp",
        "reun": "1",
        "prix": "5",
        "prixnom": "Qatar Prix de l'Arc de Triomphe",
        "numero": 17,
        "idche": 1730327,
        "age": 3,
        "entraineur": "AP. O'Brien",
        "cotedirect": 3.5,
        "predicted_position": 4.322859764099121,
        "predicted_position_tabnet": 3.988847494125366,
        "predicted_position_rf": 6.7221808433532715,
        "raw_rf_prediction": 6.7221808433532715,
        "raw_tabnet_prediction": 3.988847494125366,
        "predicted_position_base": 6.175514221191406,
        "predicted_rank": 2
      },
      {
        "comp": "1592537",
        "jour": "2025-10-05",
        "hippo": "ParisLongchamp",
        "reun": "1",
        "prix": "5",
        "prixnom": "Qatar Prix de l'Arc de Triomphe",
        "numero": 7,
        "idche": 1725716,
        "age": 4,
        "entraineur": "D. O'Meara",
        "cotedirect": 0.0,
        "predicted_position": 4.480517387390137,
        "predicted_position_tabnet": 5.983791828155518,
        "predicted_position_rf": 6.50497579574585,
        "raw_rf_prediction": 6.50497579574585,
        "raw_tabnet_prediction": 5.983791828155518,
        "predicted_position_base": 6.4007391929626465,
        "predicted_rank": 3
      },
      {
        "comp": "1592537",
        "jour": "2025-10-05",
        "hippo": "ParisLongchamp",
        "reun": "1",
        "prix": "5",
        "prixnom": "Qatar Prix de l'Arc de Triomphe",
        "numero": 10,
        "idche": 1654205,
        "age": 4,
        "entraineur": "C. Ferland",
        "cotedirect": 6.7,
        "predicted_position": 4.936227321624756,
        "predicted_position_tabnet": 4.873333930969238,
        "predicted_position_rf": 7.596358776092529,
        "raw_rf_prediction": 7.596358776092529,
        "raw_tabnet_prediction": 4.873333930969238,
        "predicted_position_base": 7.051753520965576,
        "predicted_rank": 4
      },
      {
        "comp": "1592537",
        "jour": "2025-10-05",
        "hippo": "ParisLongchamp",
        "reun": "1",
        "prix": "5",
        "prixnom": "Qatar Prix de l'Arc de Triomphe",
        "numero": 13,
        "idche": 1734424,
        "age": 3,
        "entraineur": "A. Fabre",
        "cotedirect": 23.0,
        "predicted_position": 5.306890964508057,
        "predicted_position_tabnet": 6.789987087249756,
        "predicted_position_rf": 7.779094219207764,
        "raw_rf_prediction": 7.779094219207764,
        "raw_tabnet_prediction": 6.789987087249756,
        "predicted_position_base": 7.581273078918457,
        "predicted_rank": 5
      },
      {
        "comp": "1592537",
        "jour": "2025-10-05",
        "hippo": "ParisLongchamp",
        "reun": "1",
        "prix": "5",
        "prixnom": "Qatar Prix de l'Arc de Triomphe",
        "numero": 15,
        "idche": 1759442,
        "age": 3,
        "entraineur": "T. Saito",
        "cotedirect": 9.7,
        "predicted_position": 6.189783096313477,
        "predicted_position_tabnet": 6.1569085121154785,
        "predicted_position_rf": 8.777077674865723,
        "raw_rf_prediction": 8.777077674865723,
        "raw_tabnet_prediction": 6.1569085121154785,
        "predicted_position_base": 8.253044128417969,
        "predicted_rank": 6
      },
      {
        "comp": "1592537",
        "jour": "2025-10-05",
        "hippo": "ParisLongchamp",
        "reun": "1",
        "prix": "5",
        "prixnom": "Qatar Prix de l'Arc de Triomphe",
        "numero": 3,
        "idche": 1654418,
        "age": 4,
        "entraineur": "JC. Rouget (s)",
        "cotedirect": 106.0,
        "predicted_position": 6.239269733428955,
        "predicted_position_tabnet": 9.953028678894043,
        "predicted_position_rf": 11.691901206970215,
        "raw_rf_prediction": 11.691901206970215,
        "raw_tabnet_prediction": 9.953028678894043,
        "predicted_position_base": 11.34412670135498,
        "predicted_rank": 7
      },
      {
        "comp": "1592537",
        "jour": "2025-10-05",
        "hippo": "ParisLongchamp",
        "reun": "1",
        "prix": "5",
        "prixnom": "Qatar Prix de l'Arc de Triomphe",
        "numero": 5,
        "idche": 1667455,
        "age": 4,
        "entraineur": "AP. O'Brien",
        "cotedirect": 45.0,
        "predicted_position": 6.317547798156738,
        "predicted_position_tabnet": 7.824397087097168,
        "predicted_position_rf": 9.325235366821289,
        "raw_rf_prediction": 9.325235366821289,
        "raw_tabnet_prediction": 7.824397087097168,
        "predicted_position_base": 9.025068283081055,
        "predicted_rank": 8
      },
      {
        "comp": "1592537",
        "jour": "2025-10-05",
        "hippo": "ParisLongchamp",
        "reun": "1",
        "prix": "5",
        "prixnom": "Qatar Prix de l'Arc de Triomphe",
        "numero": 1,
        "idche": 1535382,
        "age": 6,
        "entraineur": "M. Botti",
        "cotedirect": 38.0,
        "predicted_position": 6.74569034576416,
        "predicted_position_tabnet": 7.3447418212890625,
        "predicted_position_rf": 10.20969009399414,
        "raw_rf_prediction": 10.20969009399414,
        "raw_tabnet_prediction": 7.3447418212890625,
        "predicted_position_base": 9.636700630187988,
        "predicted_rank": 9
      },
      {
        "comp": "1592537",
        "jour": "2025-10-05",
        "hippo": "ParisLongchamp",
        "reun": "1",
        "prix": "5",
        "prixnom": "Qatar Prix de l'Arc de Triomphe",
        "numero": 11,
        "idche": 1741434,
        "age": 3,
        "entraineur": "FH. Graffard",
        "cotedirect": 17.0,
        "predicted_position": 6.762317657470703,
        "predicted_position_tabnet": 6.824704647064209,
        "predicted_position_rf": 9.564352989196777,
        "raw_rf_prediction": 9.564352989196777,
        "raw_tabnet_prediction": 6.824704647064209,
        "predicted_position_base": 9.016423225402832,
        "predicted_rank": 10
      },
      {
        "comp": "1592537",
        "jour": "2025-10-05",
        "hippo": "ParisLongchamp",
        "reun": "1",
        "prix": "5",
        "prixnom": "Qatar Prix de l'Arc de Triomphe",
        "numero": 9,
        "idche": 1695821,
        "age": 4,
        "entraineur": "AM. Balding",
        "cotedirect": 17.0,
        "predicted_position": 6.990495204925537,
        "predicted_position_tabnet": 6.072821617126465,
        "predicted_position_rf": 10.964820861816406,
        "raw_rf_prediction": 10.964820861816406,
        "raw_tabnet_prediction": 6.072821617126465,
        "predicted_position_base": 9.986421585083008,
        "predicted_rank": 11
      },
      {
        "comp": "1592537",
        "jour": "2025-10-05",
        "hippo": "ParisLongchamp",
        "reun": "1",
        "prix": "5",
        "prixnom": "Qatar Prix de l'Arc de Triomphe",
        "numero": 18,
        "idche": 1720861,
        "age": 3,
        "entraineur": "FH. Graffard",
        "cotedirect": 32.0,
        "predicted_position": 7.47641134262085,
        "predicted_position_tabnet": 7.0316081047058105,
        "predicted_position_rf": 11.592832565307617,
        "raw_rf_prediction": 11.592832565307617,
        "raw_tabnet_prediction": 7.0316081047058105,
        "predicted_position_base": 10.680587768554688,
        "predicted_rank": 12
      },
      {
        "comp": "1592537",
        "jour": "2025-10-05",
        "hippo": "ParisLongchamp",
        "reun": "1",
        "prix": "5",
        "prixnom": "Qatar Prix de l'Arc de Triomphe",
        "numero": 2,
        "idche": 1584656,
        "age": 5,
        "entraineur": "JJ. Murphy",
        "cotedirect": 54.0,
        "predicted_position": 7.603976726531982,
        "predicted_position_tabnet": 8.454632759094238,
        "predicted_position_rf": 10.559636116027832,
        "raw_rf_prediction": 10.559636116027832,
        "raw_tabnet_prediction": 8.454632759094238,
        "predicted_position_base": 10.138635635375977,
        "predicted_rank": 13
      },
      {
        "comp": "1592537",
        "jour": "2025-10-05",
        "hippo": "ParisLongchamp",
        "reun": "1",
        "prix": "5",
        "prixnom": "Qatar Prix de l'Arc de Triomphe",
        "numero": 8,
        "idche": 1559787,
        "age": 5,
        "entraineur": "FH. Graffard",
        "cotedirect": 20.0,
        "predicted_position": 7.721329689025879,
        "predicted_position_tabnet": 9.145232200622559,
        "predicted_position_rf": 10.582573890686035,
        "raw_rf_prediction": 10.582573890686035,
        "raw_tabnet_prediction": 9.145232200622559,
        "predicted_position_base": 10.295105934143066,
        "predicted_rank": 14
      },
      {
        "comp": "1592537",
        "jour": "2025-10-05",
        "hippo": "ParisLongchamp",
        "reun": "1",
        "prix": "5",
        "prixnom": "Qatar Prix de l'Arc de Triomphe",
        "numero": 4,
        "idche": 1654324,
        "age": 4,
        "entraineur": "A. Fabre",
        "cotedirect": 13.0,
        "predicted_position": 7.842863082885742,
        "predicted_position_tabnet": 6.8044891357421875,
        "predicted_position_rf": 12.303990364074707,
        "raw_rf_prediction": 12.303990364074707,
        "raw_tabnet_prediction": 6.8044891357421875,
        "predicted_position_base": 11.204090118408203,
        "predicted_rank": 15
      },
      {
        "comp": "1592537",
        "jour": "2025-10-05",
        "hippo": "ParisLongchamp",
        "reun": "1",
        "prix": "5",
        "prixnom": "Qatar Prix de l'Arc de Triomphe",
        "numero": 12,
        "idche": 1741620,
        "age": 3,
        "entraineur": "JC. Rouget (s)",
        "cotedirect": 48.0,
        "predicted_position": 8.192788124084473,
        "predicted_position_tabnet": 8.773333549499512,
        "predicted_position_rf": 12.4366455078125,
        "raw_rf_prediction": 12.4366455078125,
        "raw_tabnet_prediction": 8.773333549499512,
        "predicted_position_base": 11.703983306884766,
        "predicted_rank": 16
      },
      {
        "comp": "1592537",
        "jour": "2025-10-05",
        "hippo": "ParisLongchamp",
        "reun": "1",
        "prix": "5",
        "prixnom": "Qatar Prix de l'Arc de Triomphe",
        "numero": 16,
        "idche": 1759443,
        "age": 3,
        "entraineur": "H. Tanaka",
        "cotedirect": 10.0,
        "predicted_position": 8.254926681518555,
        "predicted_position_tabnet": 5.471713066101074,
        "predicted_position_rf": 12.39028263092041,
        "raw_rf_prediction": 12.39028263092041,
        "raw_tabnet_prediction": 5.471713066101074,
        "predicted_position_base": 11.006568908691406,
        "predicted_rank": 17
      },
      {
        "comp": "1592537",
        "jour": "2025-10-05",
        "hippo": "ParisLongchamp",
        "reun": "1",
        "prix": "5",
        "prixnom": "Qatar Prix de l'Arc de Triomphe",
        "numero": 14,
        "idche": 1713366,
        "age": 3,
        "entraineur": "Mme J. Harrington",
        "cotedirect": 95.0,
        "predicted_position": 9.221187591552734,
        "predicted_position_tabnet": 9.496583938598633,
        "predicted_position_rf": 12.994499206542969,
        "raw_rf_prediction": 12.994499206542969,
        "raw_tabnet_prediction": 9.496583938598633,
        "predicted_position_base": 12.294916152954102,
        "predicted_rank": 18
      }
    ]
  }
]