[
  {
    "comp": "1615258",
    "jour": "2025-10-17",
    "hippo": "Paris-Vincennes",
    "prixnom": "Prix Gudrun",
    "predictions": [
      {
        "comp": "1615258",
        "jour": "2025-10-17",
        "hippo": "Paris-Vincennes",
        "reun": "1",
        "prix": "4",
        "prixnom": "Prix Gudrun",
        "numero": 2,
        "idche": 1661355,
        "age": 4,
        "entraineur": "T. Partaix",
        "cotedirect": 15.0,
        "predicted_position": 0.8813735349295482,
        "predicted_position_tabnet": 6.273593425750732,
        "predicted_position_rf": 3.868493831185581,
        "raw_rf_prediction": 3.868493831185581,
        "raw_tabnet_prediction": 6.273593425750732,
        "predicted_position_base": 4.830533621327926,
        "predicted_rank": 1
      },
      {
        "comp": "1615258",
        "jour": "2025-10-17",
        "hippo": "Paris-Vincennes",
        "reun": "1",
        "prix": "4",
        "prixnom": "Prix Gudrun",
        "numero": 13,
        "idche": 1580046,
        "age": 5,
        "entraineur": "E. Letouzé",
        "cotedirect": 20.0,
        "predicted_position": 1.0262907369253975,
        "predicted_position_tabnet": 6.791154384613037,
        "predicted_position_rf": 3.868493831185581,
        "raw_rf_prediction": 3.868493831185581,
        "raw_tabnet_prediction": 6.791154384613037,
        "predicted_position_base": 5.037558195607711,
        "predicted_rank": 2
      },
      {
        "comp": "1615258",
        "jour": "2025-10-17",
        "hippo": "Paris-Vincennes",
        "reun": "1",
        "prix": "4",
        "prixnom": "Prix Gudrun",
        "numero": 12,
        "idche": 1646868,
        "age": 5,
        "entraineur": "M. Abrivard",
        "cotedirect": 3.0,
        "predicted_position": 2.256939624437955,
        "predicted_position_tabnet": 4.456075668334961,
        "predicted_position_rf": 3.868493831185581,
        "raw_rf_prediction": 3.868493831185581,
        "raw_tabnet_prediction": 4.456075668334961,
        "predicted_position_base": 4.103526589887191,
        "predicted_rank": 3
      },
      {
        "comp": "1615258",
        "jour": "2025-10-17",
        "hippo": "Paris-Vincennes",
        "reun": "1",
        "prix": "4",
        "prixnom": "Prix Gudrun",
        "numero": 10,
        "idche": 1685646,
        "age": 4,
        "entraineur": "T. Le Beller",
        "cotedirect": 3.3,
        "predicted_position": 2.8175770862219673,
        "predicted_position_tabnet": 4.260034561157227,
        "predicted_position_rf": 3.868493831185581,
        "raw_rf_prediction": 3.868493831185581,
        "raw_tabnet_prediction": 4.260034561157227,
        "predicted_position_base": 4.025110123174239,
        "predicted_rank": 4
      },
      {
        "comp": "1615258",
        "jour": "2025-10-17",
        "hippo": "Paris-Vincennes",
        "reun": "1",
        "prix": "4",
        "prixnom": "Prix Gudrun",
        "numero": 1,
        "idche": 1666502,
        "age": 4,
        "entraineur": "D. Locqueneux",
        "cotedirect": 30.0,
        "predicted_position": 3.094256900320559,
        "predicted_position_tabnet": 7.089996337890625,
        "predicted_position_rf": 3.868493831185581,
        "raw_rf_prediction": 3.868493831185581,
        "raw_tabnet_prediction": 7.089996337890625,
        "predicted_position_base": 5.157094833867599,
        "predicted_rank": 5
      },
      {
        "comp": "1615258",
        "jour": "2025-10-17",
        "hippo": "Paris-Vincennes",
        "reun": "1",
        "prix": "4",
        "prixnom": "Prix Gudrun",
        "numero": 9,
        "idche": 1575465,
        "age": 5,
        "entraineur": "T. Raffegeau",
        "cotedirect": 11.0,
        "predicted_position": 3.359951816332136,
        "predicted_position_tabnet": 6.197087287902832,
        "predicted_position_rf": 3.868493831185581,
        "raw_rf_prediction": 3.868493831185581,
        "raw_tabnet_prediction": 6.197087287902832,
        "predicted_position_base": 4.799931166188766,
        "predicted_rank": 6
      },
      {
        "comp": "1615258",
        "jour": "2025-10-17",
        "hippo": "Paris-Vincennes",
        "reun": "1",
        "prix": "4",
        "prixnom": "Prix Gudrun",
        "numero": 14,
        "idche": 1586206,
        "age": 5,
        "entraineur": "S. Guarato",
        "cotedirect": 19.0,
        "predicted_position": 3.546003638040815,
        "predicted_position_tabnet": 6.861557960510254,
        "predicted_position_rf": 3.868493831185581,
        "raw_rf_prediction": 3.868493831185581,
        "raw_tabnet_prediction": 6.861557960510254,
        "predicted_position_base": 5.06571948291545,
        "predicted_rank": 7
      },
      {
        "comp": "1615258",
        "jour": "2025-10-17",
        "hippo": "Paris-Vincennes",
        "reun": "1",
        "prix": "4",
        "prixnom": "Prix Gudrun",
        "numero": 3,
        "idche": 1560712,
        "age": 5,
        "entraineur": "J. Dubois",
        "cotedirect": 16.0,
        "predicted_position": 3.594626079332624,
        "predicted_position_tabnet": 7.0352091789245605,
        "predicted_position_rf": 3.868493831185581,
        "raw_rf_prediction": 3.868493831185581,
        "raw_tabnet_prediction": 7.0352091789245605,
        "predicted_position_base": 5.1351801133323205,
        "predicted_rank": 8
      },
      {
        "comp": "1615258",
        "jour": "2025-10-17",
        "hippo": "Paris-Vincennes",
        "reun": "1",
        "prix": "4",
        "prixnom": "Prix Gudrun",
        "numero": 8,
        "idche": 1552859,
        "age": 5,
        "entraineur": "S. Roger",
        "cotedirect": 27.0,
        "predicted_position": 3.651169596445356,
        "predicted_position_tabnet": 7.2371506690979,
        "predicted_position_rf": 3.868493831185581,
        "raw_rf_prediction": 3.868493831185581,
        "raw_tabnet_prediction": 7.2371506690979,
        "predicted_position_base": 5.215956566350509,
        "predicted_rank": 9
      },
      {
        "comp": "1615258",
        "jour": "2025-10-17",
        "hippo": "Paris-Vincennes",
        "reun": "1",
        "prix": "4",
        "prixnom": "Prix Gudrun",
        "numero": 7,
        "idche": 1670342,
        "age": 4,
        "entraineur": "LC. Abrivard",
        "cotedirect": 10.0,
        "predicted_position": 3.7281257790452607,
        "predicted_position_tabnet": 6.624344825744629,
        "predicted_position_rf": 3.868493831185581,
        "raw_rf_prediction": 3.868493831185581,
        "raw_tabnet_prediction": 6.624344825744629,
        "predicted_position_base": 4.970834372060348,
        "predicted_rank": 10
      },
      {
        "comp": "1615258",
        "jour": "2025-10-17",
        "hippo": "Paris-Vincennes",
        "reun": "1",
        "prix": "4",
        "prixnom": "Prix Gudrun",
        "numero": 4,
        "idche": 1581928,
        "age": 5,
        "entraineur": "T. Lamare",
        "cotedirect": 41.0,
        "predicted_position": 3.926865826380048,
        "predicted_position_tabnet": 8.221779823303223,
        "predicted_position_rf": 3.868493831185581,
        "raw_rf_prediction": 3.868493831185581,
        "raw_tabnet_prediction": 8.221779823303223,
        "predicted_position_base": 5.6098083234000695,
        "predicted_rank": 11
      },
      {
        "comp": "1615258",
        "jour": "2025-10-17",
        "hippo": "Paris-Vincennes",
        "reun": "1",
        "prix": "4",
        "prixnom": "Prix Gudrun",
        "numero": 11,
        "idche": 1558197,
        "age": 5,
        "entraineur": "LC. Abrivard",
        "cotedirect": 34.0,
        "predicted_position": 4.109869210136569,
        "predicted_position_tabnet": 7.896823406219482,
        "predicted_position_rf": 3.868493831185581,
        "raw_rf_prediction": 3.868493831185581,
        "raw_tabnet_prediction": 7.896823406219482,
        "predicted_position_base": 5.479825613515426,
        "predicted_rank": 12
      },
      {
        "comp": "1615258",
        "jour": "2025-10-17",
        "hippo": "Paris-Vincennes",
        "reun": "1",
        "prix": "4",
        "prixnom": "Prix Gudrun",
        "numero": 5,
        "idche": 1587768,
        "age": 5,
        "entraineur": "D. Locqueneux",
        "cotedirect": 80.0,
        "predicted_position": 4.117068277132307,
        "predicted_position_tabnet": 8.901074409484863,
        "predicted_position_rf": 3.868493831185581,
        "raw_rf_prediction": 3.868493831185581,
        "raw_tabnet_prediction": 8.901074409484863,
        "predicted_position_base": 5.88152611018901,
        "predicted_rank": 13
      },
      {
        "comp": "1615258",
        "jour": "2025-10-17",
        "hippo": "Paris-Vincennes",
        "reun": "1",
        "prix": "4",
        "prixnom": "Prix Gudrun",
        "numero": 6,
        "idche": 1682345,
        "age": 4,
        "entraineur": "E. Raulline",
        "cotedirect": 141.0,
        "predicted_position": 4.388976202738081,
        "predicted_position_tabnet": 9.872174263000488,
        "predicted_position_rf": 3.868493831185581,
        "raw_rf_prediction": 3.868493831185581,
        "raw_tabnet_prediction": 9.872174263000488,
        "predicted_position_base": 6.269966003911544,
        "predicted_rank": 14
      }
    ]
  }
]